{
  "header": {
    "name": "DecalData File",
    "comments": "// Instances format: rectIdx, size, renderPriority, position.x, position.y, position.z, normal.x, normal.y, normal.z, tangent.x, tangent.y, tangent.z",
    "version": 1
  },
  "instances": {
    "AsphaltRoad_damage_large_decal_01d": [
      [
        2,
        2,
        0,
        2.28458953,
        -11.551877,
        249.999985,
        0,
        0,
        1,
        -1,
        0,
        0
      ]
    ],
    "decal_graffiti": [
      [
        15,
        3,
        0,
        38.6421432,
        -68.7380066,
        255.807312,
        1,
        0,
        0,
        0,
        -1,
        0
      ],
      [
        9,
        3,
        0,
        38.6421432,
        -72.0682297,
        256.235535,
        1,
        0,
        0,
        0,
        -1,
        0
      ],
      [
        14,
        1.11877441,
        0,
        38.6442795,
        -60.6765251,
        255.494064,
        1,
        3.21005473e-07,
        -5.5929398e-08,
        3.25841398e-07,
        -0.985158682,
        0.171646073
      ]
    ]
  }
}