{"name":"guardrail_group","class":"SimGroup","persistentId":"5c9321d9-e315-42ec-8615-25d10043a227","groupPosition":"918.43103027344 -98.719268798828 71.661254882813"}
{"class":"TSStatic","persistentId":"3688f7af-f10d-41f9-8fd9-1c2ce1a632ad","__parent":"guardrail_group","position":[917.984924,-98.6522141,71.1859512],"isRenderEnabled":false,"rotationMatrix":[0.237926364,0.971283078,0,-0.971283078,0.237926364,0,0,0,1],"shapeName":"/levels/cups_canyon/art/shapes/buildings/eca_guardrailpost.dae","useInstanceRenderData":true}
{"class":"TSStatic","persistentId":"a9b3d46a-296b-4f2f-864a-1daffa38b4bb","__parent":"guardrail_group","position":[918.877136,-98.7863235,72.1365585],"isRenderEnabled":false,"rotationMatrix":[-0.969487429,0.245140746,0,-0.245140746,-0.969487429,0,0,0,1],"shapeName":"/levels/cups_canyon/art/shapes/buildings/eca_guardrail1.dae","useInstanceRenderData":true}
